stash_mcp/__init__.py
stash_mcp/main.py
stash_mcp-1.2.0.dist-info/METADATA
stash_mcp-1.2.0.dist-info/WHEEL
stash_mcp-1.2.0.dist-info/entry_points.txt
stash_mcp-1.2.0.dist-info/licenses/LICENSE
stash_mcp-1.2.0.dist-info/RECORD
