Metadata-Version: 2.4
Name: stash-mcp
Version: 1.2.0
Summary: A Model Context Protocol (MCP) server for Stash issue analysis and task management
Project-URL: Homepage, https://usestash.com
Project-URL: Documentation, https://docs.usestash.com/mcp/stash-mcp
Author-email: Stash Team <ayberk@usestash.com>
Maintainer-email: Stash Team <ayberk@usestash.com>
License: MIT
License-File: LICENSE
Keywords: ai,claude-code,copilot,cursor,issue-analysis,llm,mcp,model-context-protocol,stash,task-management
Classifier: Development Status :: 5 - Production/Stable
Classifier: Intended Audience :: Developers
Classifier: License :: OSI Approved :: MIT License
Classifier: Operating System :: OS Independent
Classifier: Programming Language :: Python :: 3
Classifier: Programming Language :: Python :: 3.10
Classifier: Programming Language :: Python :: 3.11
Classifier: Programming Language :: Python :: 3.12
Classifier: Programming Language :: Python :: 3.13
Classifier: Topic :: Office/Business :: Groupware
Classifier: Topic :: Software Development :: Bug Tracking
Classifier: Topic :: Software Development :: Libraries :: Python Modules
Classifier: Typing :: Typed
Requires-Python: >=3.10
Requires-Dist: httpx>=0.25.0
Requires-Dist: mcp>=1.13.0
Requires-Dist: python-dotenv>=1.0.0
